safe_kit/__init__.py
safe_kit/abis.py
safe_kit/adapter.py
safe_kit/contract_types.py
safe_kit/errors.py
safe_kit/factory.py
safe_kit/managers/__init__.py
safe_kit/managers/guard_manager.py
safe_kit/managers/module_manager.py
safe_kit/managers/owner_manager.py
safe_kit/managers/token_manager.py
safe_kit/multisend.py
safe_kit/py.typed
safe_kit/safe.py
safe_kit/service.py
safe_kit/types.py
safe_kit-0.0.13.dist-info/METADATA
safe_kit-0.0.13.dist-info/WHEEL
safe_kit-0.0.13.dist-info/licenses/LICENSE
safe_kit-0.0.13.dist-info/RECORD
