Metadata-Version: 2.4
Name: safe-kit
Version: 0.0.13
Summary: Python implementation of the Safe Protocol Kit
License: MIT
License-File: LICENSE
Keywords: ethereum,safe,gnosis-safe,web3,sdk,blockchain
Author: smallyu
Author-email: smallyu@users.noreply.github.com
Requires-Python: >=3.10,<4.0
Classifier: Development Status :: 3 - Alpha
Classifier: Intended Audience :: Developers
Classifier: License :: OSI Approved :: MIT License
Classifier: Programming Language :: Python :: 3
Classifier: Programming Language :: Python :: 3.10
Classifier: Programming Language :: Python :: 3.11
Classifier: Programming Language :: Python :: 3.12
Classifier: Programming Language :: Python :: 3.13
Classifier: Programming Language :: Python :: 3.14
Classifier: Topic :: Software Development :: Libraries :: Python Modules
Requires-Dist: eth-account (>=0.11.0,<0.12.0)
Requires-Dist: eth-typing (<5.0.0)
Requires-Dist: pydantic (>=2.0.0,<3.0.0)
Requires-Dist: requests (>=2.0.0,<3.0.0)
Requires-Dist: setuptools
Requires-Dist: web3 (>=6.0.0,<7.0.0)
Project-URL: Documentation, https://github.com/smallyunet/safe-kit
Project-URL: Homepage, https://github.com/smallyunet/safe-kit
Project-URL: Repository, https://github.com/smallyunet/safe-kit
